pshtt/__init__.py
pshtt/__main__.py
pshtt/_version.py
pshtt/cli.py
pshtt/models.py
pshtt/pshtt.py
pshtt/utils.py
pshtt-0.7.3.dist-info/LICENSE
pshtt-0.7.3.dist-info/METADATA
pshtt-0.7.3.dist-info/WHEEL
pshtt-0.7.3.dist-info/entry_points.txt
pshtt-0.7.3.dist-info/top_level.txt
pshtt-0.7.3.dist-info/RECORD
