Metadata-Version: 2.1
Name: pshtt
Version: 0.7.3
Summary: Scan websites for HTTPS deployment best practices
Author-email: Cybersecurity and Infrastructure Security Agency <github@cisa.dhs.gov>
License: CC0-1.0
Project-URL: homepage, https://github.com/cisagov/pshtt
Project-URL: issues, https://github.com/cisagov/pshtt/issues
Project-URL: mission, https://www.cisa.gov/cybersecurity
Project-URL: source, https://github.com/cisagov/pshtt
Keywords: https best practices
Classifier: Development Status :: 4 - Beta
Classifier: Environment :: Console
Classifier: Intended Audience :: Developers
Classifier: Natural Language :: English
Classifier: Operating System :: OS Independent
Classifier: Programming Language :: Python :: 3
Classifier: Programming Language :: Python :: 3 :: Only
Classifier: Programming Language :: Python :: 3.7
Classifier: Programming Language :: Python :: 3.8
Classifier: Programming Language :: Python :: 3.9
Classifier: Programming Language :: Python :: 3.10
Classifier: Programming Language :: Python :: Implementation :: CPython
Requires-Python: >=3.7
License-File: LICENSE
Requires-Dist: docopt >=0.6.2
Requires-Dist: publicsuffixlist[update] >=0.9.2
Requires-Dist: pyopenssl >=17.5.0
Requires-Dist: pytablereader >=0.15.0
Requires-Dist: pytablewriter >=0.27.2
Requires-Dist: python-dateutil >=2.7.3
Requires-Dist: pytz >=2018.5
Requires-Dist: requests >=2.18.4
Requires-Dist: sslyze <5.0.0,>=3.0.0
Requires-Dist: wget >=3.2
Provides-Extra: dev
Requires-Dist: types-docopt ; extra == 'dev'
Requires-Dist: types-pyOpenSSL ; extra == 'dev'
Requires-Dist: types-requests ; extra == 'dev'
Requires-Dist: types-urllib3 ; extra == 'dev'
Provides-Extra: test
Requires-Dist: coverage ; extra == 'test'
Requires-Dist: coveralls ; extra == 'test'
Requires-Dist: pre-commit ; extra == 'test'
Requires-Dist: pytest-cov ; extra == 'test'
Requires-Dist: pytest ; extra == 'test'
